castme/__init__.py
castme/assets/castme.toml.template
castme/backends/__init__.py
castme/backends/chromecast.py
castme/backends/local.py
castme/config.py
castme/main.py
castme/messages.py
castme/player.py
castme/song.py
castme/subsonic.py
castme-0.3.1.dist-info/LICENSE
castme-0.3.1.dist-info/METADATA
castme-0.3.1.dist-info/WHEEL
castme-0.3.1.dist-info/entry_points.txt
castme-0.3.1.dist-info/RECORD
