Metadata-Version: 2.1
Name: castme
Version: 0.3.1
Summary: REPL to stream music from a Subsonic server to a chromecast
Home-page: https://github.com/Blizarre/castme
License: GPL-3.0-only
Keywords: subsonic,chromecast
Author: Simon Marache-Francisco
Author-email: pypi@simon.marache.net
Requires-Python: >=3.10,<4.0
Classifier: License :: OSI Approved :: GNU General Public License v3 (GPLv3)
Classifier: Programming Language :: Python :: 3
Classifier: Programming Language :: Python :: 3.10
Classifier: Programming Language :: Python :: 3.11
Classifier: Programming Language :: Python :: 3.12
Classifier: Programming Language :: Python :: 3.13
Requires-Dist: pychromecast (>=13.1.0,<14.0.0)
Requires-Dist: pygame (>=2.6.1,<3.0.0)
Requires-Dist: termcolor (>=2.5.0,<3.0.0)
Requires-Dist: types-requests (>=2.32.0.20240914,<3.0.0.0)
Requires-Dist: zeroconf (>=0.135.0,<0.136.0)
Project-URL: Bug Tracker, https://github.com/Blizarre/castme/issues
Project-URL: Repository, https://github.com/Blizarre/castme
